[
    {
      "infos": {
        "firstName": "Ava",
        "lastName": "Johnson",
        "birthDate": "11/20/1987"
      },
      "contact": {
        "street": "Broadway",
        "city": "New York",
        "state": { "name": "Arizona", "abbreviation": "AZ" },
        "zip": "95052"
      },
      "onboarding": { "startDate": "12/23/2023", "department": "Engineering" }
    },
    {
      "infos": {
        "firstName": "James",
        "lastName": "Miller",
        "birthDate": "12/24/1995"
      },
      "contact": {
        "street": "Cedar Street",
        "city": "Houston",
        "state": { "name": "Alabama", "abbreviation": "AL" },
        "zip": "98235"
      },
      "onboarding": { "startDate": "11/23/2022", "department": "Engineering" }
    },
    {
      "infos": {
        "firstName": "Emma",
        "lastName": "Smith",
        "birthDate": "01/15/1990"
      },
      "contact": {
        "street": "Oak Street",
        "city": "San Francisco",
        "state": { "name": "California", "abbreviation": "CA" },
        "zip": "94101"
      },
      "onboarding": { "startDate": "10/01/2021", "department": "Engineering" }
    },
    {
      "infos": {
        "firstName": "Oliver",
        "lastName": "Brown",
        "birthDate": "02/28/1988"
      },
      "contact": {
        "street": "Pine Street",
        "city": "Los Angeles",
        "state": { "name": "California", "abbreviation": "CA" },
        "zip": "90001"
      },
      "onboarding": { "startDate": "09/15/2020", "department": "Engineering" }
    },
    {
      "infos": {
        "firstName": "Ava",
        "lastName": "Johnson",
        "birthDate": "11/21/1987"
      },
      "contact": {
        "street": "Broadway",
        "city": "New York",
        "state": { "name": "Arizona", "abbreviation": "AZ" },
        "zip": "95052"
      },
      "onboarding": { "startDate": "12/24/2023", "department": "Engineering" }
    },
    {
      "infos": {
        "firstName": "James",
        "lastName": "Miller",
        "birthDate": "12/25/1995"
      },
      "contact": {
        "street": "Cedar Street",
        "city": "Houston",
        "state": { "name": "Alabama", "abbreviation": "AL" },
        "zip": "98235"
      },
      "onboarding": { "startDate": "11/24/2022", "department": "Engineering" }
    },
    {
      "infos": {
        "firstName": "Emma",
        "lastName": "Smith",
        "birthDate": "01/16/1990"
      },
      "contact": {
        "street": "Oak Street",
        "city": "San Francisco",
        "state": { "name": "California", "abbreviation": "CA" },
        "zip": "94101"
      },
      "onboarding": { "startDate": "10/02/2021", "department": "Engineering" }
    },
    {
      "infos": {
        "firstName": "Oliver",
        "lastName": "Brown",
        "birthDate": "02/29/1988"
      },
      "contact": {
        "street": "Pine Street",
        "city": "Los Angeles",
        "state": { "name": "California", "abbreviation": "CA" },
        "zip": "90001"
      },
      "onboarding": { "startDate": "09/16/2020", "department": "Engineering" }
    },
  {
      "infos": {
        "firstName": "Oliver",
        "lastName": "Brown",
        "birthDate": "02/28/1988"
      },
      "contact": {
        "street": "Pine Street",
        "city": "Los Angeles",
        "state": { "name": "California", "abbreviation": "CA" },
        "zip": "90001"
      },
      "onboarding": { "startDate": "09/15/2020", "department": "Engineering" }
    },
  {
      "infos": {
        "firstName": "Ava",
        "lastName": "Johnson",
        "birthDate": "11/20/1987"
      },
      "contact": {
        "street": "Broadway",
        "city": "New York",
        "state": { "name": "Arizona", "abbreviation": "AZ" },
        "zip": "95052"
      },
      "onboarding": { "startDate": "12/23/2023", "department": "Engineering" }
    },
    {
      "infos": {
        "firstName": "James",
        "lastName": "Miller",
        "birthDate": "12/24/1995"
      },
      "contact": {
        "street": "Cedar Street",
        "city": "Houston",
        "state": { "name": "Alabama", "abbreviation": "AL" },
        "zip": "98235"
      },
      "onboarding": { "startDate": "11/23/2022", "department": "Engineering" }
    },
    {
      "infos": {
        "firstName": "Emma",
        "lastName": "Smith",
        "birthDate": "01/15/1990"
      },
      "contact": {
        "street": "Oak Street",
        "city": "San Francisco",
        "state": { "name": "California", "abbreviation": "CA" },
        "zip": "94101"
      },
      "onboarding": { "startDate": "10/01/2021", "department": "Engineering" }
    },
    {
      "infos": {
        "firstName": "Oliver",
        "lastName": "Brown",
        "birthDate": "02/28/1988"
      },
      "contact": {
        "street": "Pine Street",
        "city": "Los Angeles",
        "state": { "name": "California", "abbreviation": "CA" },
        "zip": "90001"
      },
      "onboarding": { "startDate": "09/15/2020", "department": "Engineering" }
    },
  {
      "infos": {
        "firstName": "Ava",
        "lastName": "Johnson",
        "birthDate": "11/20/1987"
      },
      "contact": {
        "street": "Broadway",
        "city": "New York",
        "state": { "name": "Arizona", "abbreviation": "AZ" },
        "zip": "95052"
      },
      "onboarding": { "startDate": "12/23/2023", "department": "Engineering" }
    },
    {
      "infos": {
        "firstName": "James",
        "lastName": "Miller",
        "birthDate": "12/24/1995"
      },
      "contact": {
        "street": "Cedar Street",
        "city": "Houston",
        "state": { "name": "Alabama", "abbreviation": "AL" },
        "zip": "98235"
      },
      "onboarding": { "startDate": "11/23/2022", "department": "Engineering" }
    },
    {
      "infos": {
        "firstName": "Emma",
        "lastName": "Smith",
        "birthDate": "01/15/1990"
      },
      "contact": {
        "street": "Oak Street",
        "city": "San Francisco",
        "state": { "name": "California", "abbreviation": "CA" },
        "zip": "94101"
      },
      "onboarding": { "startDate": "10/01/2021", "department": "Engineering" }
    },
    {
      "infos": {
        "firstName": "Oliver",
        "lastName": "Brown",
        "birthDate": "02/28/1988"
      },
      "contact": {
        "street": "Pine Street",
        "city": "Los Angeles",
        "state": { "name": "California", "abbreviation": "CA" },
        "zip": "90001"
      },
      "onboarding": { "startDate": "09/15/2020", "department": "Engineering" }
    },
  {
      "infos": {
        "firstName": "Ava",
        "lastName": "Johnson",
        "birthDate": "11/20/1987"
      },
      "contact": {
        "street": "Broadway",
        "city": "New York",
        "state": { "name": "Arizona", "abbreviation": "AZ" },
        "zip": "95052"
      },
      "onboarding": { "startDate": "12/23/2023", "department": "Engineering" }
    },
    {
      "infos": {
        "firstName": "James",
        "lastName": "Miller",
        "birthDate": "12/24/1995"
      },
      "contact": {
        "street": "Cedar Street",
        "city": "Houston",
        "state": { "name": "Alabama", "abbreviation": "AL" },
        "zip": "98235"
      },
      "onboarding": { "startDate": "11/23/2022", "department": "Engineering" }
    },
    {
      "infos": {
        "firstName": "Emma",
        "lastName": "Smith",
        "birthDate": "01/15/1990"
      },
      "contact": {
        "street": "Oak Street",
        "city": "San Francisco",
        "state": { "name": "California", "abbreviation": "CA" },
        "zip": "94101"
      },
      "onboarding": { "startDate": "10/01/2021", "department": "Engineering" }
    },
    {
      "infos": {
        "firstName": "Oliver",
        "lastName": "Brown",
        "birthDate": "02/28/1988"
      },
      "contact": {
        "street": "Pine Street",
        "city": "Los Angeles",
        "state": { "name": "California", "abbreviation": "CA" },
        "zip": "90001"
      },
      "onboarding": { "startDate": "09/15/2020", "department": "Engineering" }
    },
    {
      "infos": {
        "firstName": "Ava",
        "lastName": "Johnson",
        "birthDate": "11/20/1987"
      },
      "contact": {
        "street": "Broadway",
        "city": "New York",
        "state": { "name": "Arizona", "abbreviation": "AZ" },
        "zip": "95052"
      },
      "onboarding": { "startDate": "12/23/2023", "department": "Engineering" }
    },
    {
      "infos": {
        "firstName": "James",
        "lastName": "Miller",
        "birthDate": "12/24/1995"
      },
      "contact": {
        "street": "Cedar Street",
        "city": "Houston",
        "state": { "name": "Alabama", "abbreviation": "AL" },
        "zip": "98235"
      },
      "onboarding": { "startDate": "11/23/2022", "department": "Engineering" }
    },
    {
      "infos": {
        "firstName": "Emma",
        "lastName": "Smith",
        "birthDate": "01/15/1990"
      },
      "contact": {
        "street": "Oak Street",
        "city": "San Francisco",
        "state": { "name": "California", "abbreviation": "CA" },
        "zip": "94101"
      },
      "onboarding": { "startDate": "10/01/2021", "department": "Engineering" }
    },
    {
      "infos": {
        "firstName": "Oliver",
        "lastName": "Brown",
        "birthDate": "02/28/1988"
      },
      "contact": {
        "street": "Pine Street",
        "city": "Los Angeles",
        "state": { "name": "California", "abbreviation": "CA" },
        "zip": "90001"
      },
      "onboarding": { "startDate": "09/15/2020", "department": "Engineering" }
    },
    {
      "infos": {
        "firstName": "Ava",
        "lastName": "Johnson",
        "birthDate": "11/21/1987"
      },
      "contact": {
        "street": "Broadway",
        "city": "New York",
        "state": { "name": "Arizona", "abbreviation": "AZ" },
        "zip": "95052"
      },
      "onboarding": { "startDate": "12/24/2023", "department": "Engineering" }
    },
    {
      "infos": {
        "firstName": "James",
        "lastName": "Miller",
        "birthDate": "12/25/1995"
      },
      "contact": {
        "street": "Cedar Street",
        "city": "Houston",
        "state": { "name": "Alabama", "abbreviation": "AL" },
        "zip": "98235"
      },
      "onboarding": { "startDate": "11/24/2022", "department": "Engineering" }
    },
    {
      "infos": {
        "firstName": "Emma",
        "lastName": "Smith",
        "birthDate": "01/16/1990"
      },
      "contact": {
        "street": "Oak Street",
        "city": "San Francisco",
        "state": { "name": "California", "abbreviation": "CA" },
        "zip": "94101"
      },
      "onboarding": { "startDate": "10/02/2021", "department": "Engineering" }
    },
    {
      "infos": {
        "firstName": "Oliver",
        "lastName": "Brown",
        "birthDate": "02/29/1988"
      },
      "contact": {
        "street": "Pine Street",
        "city": "Los Angeles",
        "state": { "name": "California", "abbreviation": "CA" },
        "zip": "90001"
      },
      "onboarding": { "startDate": "09/16/2020", "department": "Engineering" }
    },
  {
      "infos": {
        "firstName": "Oliver",
        "lastName": "Brown",
        "birthDate": "02/28/1988"
      },
      "contact": {
        "street": "Pine Street",
        "city": "Los Angeles",
        "state": { "name": "California", "abbreviation": "CA" },
        "zip": "90001"
      },
      "onboarding": { "startDate": "09/15/2020", "department": "Engineering" }
    },
  {
      "infos": {
        "firstName": "Ava",
        "lastName": "Johnson",
        "birthDate": "11/20/1987"
      },
      "contact": {
        "street": "Broadway",
        "city": "New York",
        "state": { "name": "Arizona", "abbreviation": "AZ" },
        "zip": "95052"
      },
      "onboarding": { "startDate": "12/23/2023", "department": "Engineering" }
    },
    {
      "infos": {
        "firstName": "James",
        "lastName": "Miller",
        "birthDate": "12/24/1995"
      },
      "contact": {
        "street": "Cedar Street",
        "city": "Houston",
        "state": { "name": "Alabama", "abbreviation": "AL" },
        "zip": "98235"
      },
      "onboarding": { "startDate": "11/23/2022", "department": "Engineering" }
    },
    {
      "infos": {
        "firstName": "Emma",
        "lastName": "Smith",
        "birthDate": "01/15/1990"
      },
      "contact": {
        "street": "Oak Street",
        "city": "San Francisco",
        "state": { "name": "California", "abbreviation": "CA" },
        "zip": "94101"
      },
      "onboarding": { "startDate": "10/01/2021", "department": "Engineering" }
    },
    {
      "infos": {
        "firstName": "Oliver",
        "lastName": "Brown",
        "birthDate": "02/28/1988"
      },
      "contact": {
        "street": "Pine Street",
        "city": "Los Angeles",
        "state": { "name": "California", "abbreviation": "CA" },
        "zip": "90001"
      },
      "onboarding": { "startDate": "09/15/2020", "department": "Engineering" }
    },
  {
      "infos": {
        "firstName": "Ava",
        "lastName": "Johnson",
        "birthDate": "11/20/1987"
      },
      "contact": {
        "street": "Broadway",
        "city": "New York",
        "state": { "name": "Arizona", "abbreviation": "AZ" },
        "zip": "95052"
      },
      "onboarding": { "startDate": "12/23/2023", "department": "Engineering" }
    },
    {
      "infos": {
        "firstName": "James",
        "lastName": "Miller",
        "birthDate": "12/24/1995"
      },
      "contact": {
        "street": "Cedar Street",
        "city": "Houston",
        "state": { "name": "Alabama", "abbreviation": "AL" },
        "zip": "98235"
      },
      "onboarding": { "startDate": "11/23/2022", "department": "Engineering" }
    },
    {
      "infos": {
        "firstName": "Emma",
        "lastName": "Smith",
        "birthDate": "01/15/1990"
      },
      "contact": {
        "street": "Oak Street",
        "city": "San Francisco",
        "state": { "name": "California", "abbreviation": "CA" },
        "zip": "94101"
      },
      "onboarding": { "startDate": "10/01/2021", "department": "Engineering" }
    },
    {
      "infos": {
        "firstName": "Oliver",
        "lastName": "Brown",
        "birthDate": "02/28/1988"
      },
      "contact": {
        "street": "Pine Street",
        "city": "Los Angeles",
        "state": { "name": "California", "abbreviation": "CA" },
        "zip": "90001"
      },
      "onboarding": { "startDate": "09/15/2020", "department": "Engineering" }
    },
  {
      "infos": {
        "firstName": "Ava",
        "lastName": "Johnson",
        "birthDate": "11/20/1987"
      },
      "contact": {
        "street": "Broadway",
        "city": "New York",
        "state": { "name": "Arizona", "abbreviation": "AZ" },
        "zip": "95052"
      },
      "onboarding": { "startDate": "12/23/2023", "department": "Engineering" }
    },
    {
      "infos": {
        "firstName": "James",
        "lastName": "Miller",
        "birthDate": "12/24/1995"
      },
      "contact": {
        "street": "Cedar Street",
        "city": "Houston",
        "state": { "name": "Alabama", "abbreviation": "AL" },
        "zip": "98235"
      },
      "onboarding": { "startDate": "11/23/2022", "department": "Engineering" }
    },
    {
      "infos": {
        "firstName": "Emma",
        "lastName": "Smith",
        "birthDate": "01/15/1990"
      },
      "contact": {
        "street": "Oak Street",
        "city": "San Francisco",
        "state": { "name": "California", "abbreviation": "CA" },
        "zip": "94101"
      },
      "onboarding": { "startDate": "10/01/2021", "department": "Engineering" }
    },
    {
      "infos": {
        "firstName": "Oliver",
        "lastName": "Brown",
        "birthDate": "02/28/1988"
      },
      "contact": {
        "street": "Pine Street",
        "city": "Los Angeles",
        "state": { "name": "California", "abbreviation": "CA" },
        "zip": "90001"
      },
      "onboarding": { "startDate": "09/15/2020", "department": "Engineering" }
    },
    {
      "infos": {
        "firstName": "Ava",
        "lastName": "Johnson",
        "birthDate": "11/20/1987"
      },
      "contact": {
        "street": "Broadway",
        "city": "New York",
        "state": { "name": "Arizona", "abbreviation": "AZ" },
        "zip": "95052"
      },
      "onboarding": { "startDate": "12/23/2023", "department": "Engineering" }
    },
    {
      "infos": {
        "firstName": "James",
        "lastName": "Miller",
        "birthDate": "12/24/1995"
      },
      "contact": {
        "street": "Cedar Street",
        "city": "Houston",
        "state": { "name": "Alabama", "abbreviation": "AL" },
        "zip": "98235"
      },
      "onboarding": { "startDate": "11/23/2022", "department": "Engineering" }
    },
    {
      "infos": {
        "firstName": "Emma",
        "lastName": "Smith",
        "birthDate": "01/15/1990"
      },
      "contact": {
        "street": "Oak Street",
        "city": "San Francisco",
        "state": { "name": "California", "abbreviation": "CA" },
        "zip": "94101"
      },
      "onboarding": { "startDate": "10/01/2021", "department": "Engineering" }
    },
    {
      "infos": {
        "firstName": "Oliver",
        "lastName": "Brown",
        "birthDate": "02/28/1988"
      },
      "contact": {
        "street": "Pine Street",
        "city": "Los Angeles",
        "state": { "name": "California", "abbreviation": "CA" },
        "zip": "90001"
      },
      "onboarding": { "startDate": "09/15/2020", "department": "Engineering" }
    },
    {
      "infos": {
        "firstName": "Ava",
        "lastName": "Johnson",
        "birthDate": "11/21/1987"
      },
      "contact": {
        "street": "Broadway",
        "city": "New York",
        "state": { "name": "Arizona", "abbreviation": "AZ" },
        "zip": "95052"
      },
      "onboarding": { "startDate": "12/24/2023", "department": "Engineering" }
    },
    {
      "infos": {
        "firstName": "James",
        "lastName": "Miller",
        "birthDate": "12/25/1995"
      },
      "contact": {
        "street": "Cedar Street",
        "city": "Houston",
        "state": { "name": "Alabama", "abbreviation": "AL" },
        "zip": "98235"
      },
      "onboarding": { "startDate": "11/24/2022", "department": "Engineering" }
    },
    {
      "infos": {
        "firstName": "Emma",
        "lastName": "Smith",
        "birthDate": "01/16/1990"
      },
      "contact": {
        "street": "Oak Street",
        "city": "San Francisco",
        "state": { "name": "California", "abbreviation": "CA" },
        "zip": "94101"
      },
      "onboarding": { "startDate": "10/02/2021", "department": "Engineering" }
    },
    {
      "infos": {
        "firstName": "Oliver",
        "lastName": "Brown",
        "birthDate": "02/29/1988"
      },
      "contact": {
        "street": "Pine Street",
        "city": "Los Angeles",
        "state": { "name": "California", "abbreviation": "CA" },
        "zip": "90001"
      },
      "onboarding": { "startDate": "09/16/2020", "department": "Engineering" }
    },
  {
      "infos": {
        "firstName": "Oliver",
        "lastName": "Brown",
        "birthDate": "02/28/1988"
      },
      "contact": {
        "street": "Pine Street",
        "city": "Los Angeles",
        "state": { "name": "California", "abbreviation": "CA" },
        "zip": "90001"
      },
      "onboarding": { "startDate": "09/15/2020", "department": "Engineering" }
    },
  {
      "infos": {
        "firstName": "Ava",
        "lastName": "Johnson",
        "birthDate": "11/20/1987"
      },
      "contact": {
        "street": "Broadway",
        "city": "New York",
        "state": { "name": "Arizona", "abbreviation": "AZ" },
        "zip": "95052"
      },
      "onboarding": { "startDate": "12/23/2023", "department": "Engineering" }
    },
    {
      "infos": {
        "firstName": "James",
        "lastName": "Miller",
        "birthDate": "12/24/1995"
      },
      "contact": {
        "street": "Cedar Street",
        "city": "Houston",
        "state": { "name": "Alabama", "abbreviation": "AL" },
        "zip": "98235"
      },
      "onboarding": { "startDate": "11/23/2022", "department": "Engineering" }
    },
    {
      "infos": {
        "firstName": "Emma",
        "lastName": "Smith",
        "birthDate": "01/15/1990"
      },
      "contact": {
        "street": "Oak Street",
        "city": "San Francisco",
        "state": { "name": "California", "abbreviation": "CA" },
        "zip": "94101"
      },
      "onboarding": { "startDate": "10/01/2021", "department": "Engineering" }
    },
    {
      "infos": {
        "firstName": "Oliver",
        "lastName": "Brown",
        "birthDate": "02/28/1988"
      },
      "contact": {
        "street": "Pine Street",
        "city": "Los Angeles",
        "state": { "name": "California", "abbreviation": "CA" },
        "zip": "90001"
      },
      "onboarding": { "startDate": "09/15/2020", "department": "Engineering" }
    },
  {
      "infos": {
        "firstName": "Ava",
        "lastName": "Johnson",
        "birthDate": "11/20/1987"
      },
      "contact": {
        "street": "Broadway",
        "city": "New York",
        "state": { "name": "Arizona", "abbreviation": "AZ" },
        "zip": "95052"
      },
      "onboarding": { "startDate": "12/23/2023", "department": "Engineering" }
    },
    {
      "infos": {
        "firstName": "James",
        "lastName": "Miller",
        "birthDate": "12/24/1995"
      },
      "contact": {
        "street": "Cedar Street",
        "city": "Houston",
        "state": { "name": "Alabama", "abbreviation": "AL" },
        "zip": "98235"
      },
      "onboarding": { "startDate": "11/23/2022", "department": "Engineering" }
    },
    {
      "infos": {
        "firstName": "Emma",
        "lastName": "Smith",
        "birthDate": "01/15/1990"
      },
      "contact": {
        "street": "Oak Street",
        "city": "San Francisco",
        "state": { "name": "California", "abbreviation": "CA" },
        "zip": "94101"
      },
      "onboarding": { "startDate": "10/01/2021", "department": "Engineering" }
    },
    {
      "infos": {
        "firstName": "Oliver",
        "lastName": "Brown",
        "birthDate": "02/28/1988"
      },
      "contact": {
        "street": "Pine Street",
        "city": "Los Angeles",
        "state": { "name": "California", "abbreviation": "CA" },
        "zip": "90001"
      },
      "onboarding": { "startDate": "09/15/2020", "department": "Engineering" }
    },
  {
      "infos": {
        "firstName": "Ava",
        "lastName": "Johnson",
        "birthDate": "11/20/1987"
      },
      "contact": {
        "street": "Broadway",
        "city": "New York",
        "state": { "name": "Arizona", "abbreviation": "AZ" },
        "zip": "95052"
      },
      "onboarding": { "startDate": "12/23/2023", "department": "Engineering" }
    },
    {
      "infos": {
        "firstName": "James",
        "lastName": "Miller",
        "birthDate": "12/24/1995"
      },
      "contact": {
        "street": "Cedar Street",
        "city": "Houston",
        "state": { "name": "Alabama", "abbreviation": "AL" },
        "zip": "98235"
      },
      "onboarding": { "startDate": "11/23/2022", "department": "Engineering" }
    },
    {
      "infos": {
        "firstName": "Emma",
        "lastName": "Smith",
        "birthDate": "01/15/1990"
      },
      "contact": {
        "street": "Oak Street",
        "city": "San Francisco",
        "state": { "name": "California", "abbreviation": "CA" },
        "zip": "94101"
      },
      "onboarding": { "startDate": "10/01/2021", "department": "Engineering" }
    },
    {
      "infos": {
        "firstName": "Oliver",
        "lastName": "Brown",
        "birthDate": "02/28/1988"
      },
      "contact": {
        "street": "Pine Street",
        "city": "Los Angeles",
        "state": { "name": "California", "abbreviation": "CA" },
        "zip": "90001"
      },
      "onboarding": { "startDate": "09/15/2020", "department": "Engineering" }
    }
  ]